autoluv/__init__.py
autoluv/core.py
autoluv/main.py
autoluv-0.1.dist-info/METADATA
autoluv-0.1.dist-info/WHEEL
autoluv-0.1.dist-info/entry_points.txt
autoluv-0.1.dist-info/top_level.txt
autoluv-0.1.dist-info/RECORD
