Metadata-Version: 2.1
Name: autoluv
Version: 0.1
Summary: tool for autoluv
Home-page: https://github.com/project/autoluv
Author: beanliu
Classifier: Programming Language :: Python :: 3
Classifier: Programming Language :: Python :: 2
Classifier: Operating System :: OS Independent
